{
    "benchmarks": {
        "network": {
            "service_chain": {
                "EXT": {
                    "result": {
                        "bidirectional": true,
                        "compute_nodes": {},
                        "flow_count": 1024,
                        "profile": "traffic_profile_IMIX",
                        "result": {
                            "IMIX": {
                                "iteration_stats": {
                                    "ndr_pdr": [
                                        {
                                            "drop_pct": 406880908,
                                            "drop_percentage": 93.9678354692277,
                                            "rx_pkts": 26119284,
                                            "rx_pps": 987368.6984116435,
                                            "time_ms": 1544206683606,
                                            "total_tx_pps": 14433339,
                                            "tx_pkts": 433000192,
                                            "tx_pps": 16368398,
                                            "warning": "WARNING: There is a significant difference between requested TX rate (16368398) and actual TX rate (14433339). The traffic generator may not have sufficient CPU to achieve the requested TX rate."
                                        },
                                        {
                                            "drop_pct": 219488376,
                                            "drop_percentage": 89.39510075870524,
                                            "rx_pkts": 26037804,
                                            "rx_pps": 867925.9516080609,
                                            "time_ms": 1544206715647,
                                            "total_tx_pps": 8184206,
                                            "tx_pkts": 245526180,
                                            "tx_pps": 8184198
                                        },
                                        {
                                            "drop_pct": 96638698,
                                            "drop_percentage": 78.71963942009432,
                                            "rx_pkts": 26124438,
                                            "rx_pps": 870813.2096831085,
                                            "time_ms": 1544206747681,
                                            "total_tx_pps": 4092104,
                                            "tx_pkts": 122763136,
                                            "tx_pps": 4092098
                                        },
                                        {
                                            "drop_pct": 35234322,
                                            "drop_percentage": 57.402064995734555,
                                            "rx_pkts": 26147306,
                                            "rx_pps": 871574.1971960731,
                                            "time_ms": 1544206779718,
                                            "total_tx_pps": 2046054,
                                            "tx_pkts": 61381628,
                                            "tx_pps": 2046048
                                        },
                                        {
                                            "drop_pct": 4495523,
                                            "drop_percentage": 14.64774782295276,
                                            "rx_pkts": 26195359,
                                            "rx_pps": 873174.0243117156,
                                            "time_ms": 1544206811762,
                                            "total_tx_pps": 1023029,
                                            "tx_pkts": 30690882,
                                            "tx_pps": 1023024
                                        },
                                        {
                                            "drop_pct": 0,
                                            "drop_percentage": 0.0,
                                            "rx_pkts": 15345510,
                                            "rx_pps": 511512.0,
                                            "time_ms": 1544206843801,
                                            "total_tx_pps": 511517,
                                            "tx_pkts": 15345510,
                                            "tx_pps": 511512
                                        },
                                        {
                                            "drop_pct": 0,
                                            "drop_percentage": 0.0,
                                            "rx_pkts": 23018196,
                                            "rx_pps": 767268.0,
                                            "time_ms": 1544206875838,
                                            "total_tx_pps": 767273,
                                            "tx_pkts": 23018196,
                                            "tx_pps": 767268
                                        },
                                        {
                                            "drop_pct": 425503,
                                            "drop_percentage": 1.5844733579106816,
                                            "rx_pkts": 26429035,
                                            "rx_pps": 880962.6501155968,
                                            "time_ms": 1544206907871,
                                            "total_tx_pps": 895151,
                                            "tx_pkts": 26854538,
                                            "tx_pps": 895146
                                        },
                                        {
                                            "drop_pct": 1791,
                                            "drop_percentage": 0.007182280915969799,
                                            "rx_pkts": 24934577,
                                            "rx_pps": 831146.3004500896,
                                            "time_ms": 1544206939906,
                                            "total_tx_pps": 831212,
                                            "tx_pkts": 24936368,
                                            "tx_pps": 831206
                                        },
                                        {
                                            "drop_pct": 2750,
                                            "drop_percentage": 0.01146919083398951,
                                            "rx_pkts": 23974530,
                                            "rx_pps": 799146.3338685622,
                                            "time_ms": 1544206971957,
                                            "total_tx_pps": 799242,
                                            "tx_pkts": 23977280,
                                            "tx_pps": 799238
                                        },
                                        {
                                            "drop_pct": 68,
                                            "drop_percentage": 0.00028938955741186664,
                                            "ndr_pps": 391626,
                                            "rx_pkts": 23497670,
                                            "rx_pps": 783249.7333505037,
                                            "time_ms": 1544207003997,
                                            "total_tx_pps": 783257,
                                            "tx_pkts": 23497738,
                                            "tx_pps": 783252
                                        }
                                    ]
                                },
                                "ndr": {
                                    "duration_sec": 30.0,
                                    "initial_rate_type": "rate_percent",
                                    "l2frame_size": "IMIX",
                                    "load_percent_per_direction": 4.78515625,
                                    "rate_bps": 2392578124.0,
                                    "rate_percent": 9.5703125,
                                    "rate_pps": 783252,
                                    "stats": {
                                        "0": {
                                            "avg_delay_usec": 323,
                                            "drop_pct": 52,
                                            "drop_percentage": 0.0004425957936887372,
                                            "max_delay_usec": 709,
                                            "min_delay_usec": 30,
                                            "rx_pkts": 11748817,
                                            "tx_pkts": 11748869
                                        },
                                        "1": {
                                            "avg_delay_usec": 300,
                                            "drop_pct": 16,
                                            "drop_percentage": 0.00013618332113499607,
                                            "max_delay_usec": 632,
                                            "min_delay_usec": 30,
                                            "rx_pkts": 11748853,
                                            "tx_pkts": 11748869
                                        },
                                        "overall": {
                                            "avg_delay_usec": 311,
                                            "drop_pct": 68,
                                            "drop_percentage": 0.0002893895574118666,
                                            "max_delay_usec": 709,
                                            "min_delay_usec": 30,
                                            "rx_pkts": 23497670,
                                            "tx_pkts": 23497738
                                        },
                                        "total_tx_rate": 783257
                                    },
                                    "time_taken_sec": 352.4291820526123,
                                    "timestamp_sec": 1544207003.998229
                                }
                            }
                        },
                        "service_chain_count": 1
                    }
                }
            },
            "versions": {
                "Traffic_Generator": {
                    "build_date": "Nov 13 2017",
                    "build_time": "10:58:17",
                    "built_by": "hhaim",
                    "mode": "STL",
                    "version": "v2.32"
                }
            }
        }
    },
    "config": {
        "availability_zone": null,
        "check_traffic_time_sec": 200,
        "compute_nodes": null,
        "config": "/tmp/nfvbench/nfvbench_config.cfg",
        "debug": false,
        "duration_sec": 30.0,
        "external_networks": {
            "left": "nfvbench-net0",
            "right": "nfvbench-net1"
        },
        "factory_class": "BasicFactory",
        "factory_module": "nfvbench.factory",
        "flavor": {
            "disk": 0,
            "extra_specs": {
                "hw:cpu_policy": "dedicated",
                "hw:mem_page_size": "large"
            },
            "ram": 4096,
            "vcpus": 2
        },
        "flavor_type": "nfvbench.medium",
        "flow_count": 1024,
        "fluentd": [
            {
                "ip": "127.0.0.1",
                "logging_tag": null,
                "port": 24224,
                "result_tag": null
            }
        ],
        "frame_sizes": [
            "IMIX"
        ],
        "generator_profile": "trex-local",
        "generic_poll_sec": 2,
        "generic_retry_count": 100,
        "host": "0.0.0.0",
        "internal_networks": {
            "left": {
                "cidr": "172.16.10.0/24",
                "name": "nfvbench-net0",
                "network_type": "vlan",
                "physical_network": null,
                "segmentation_id": null,
                "subnet": "nfvbench-subnet0"
            },
            "middle": {
                "cidr": "192.168.3.0/24",
                "name": "nfvbench-net2",
                "network_type": "vlan",
                "physical_network": null,
                "segmentation_id": null,
                "subnet": "nfvbench-subnet2"
            },
            "right": {
                "cidr": "172.16.20.0/24",
                "name": "nfvbench-net1",
                "network_type": "vlan",
                "physical_network": null,
                "segmentation_id": null,
                "subnet": "nfvbench-subnet1"
            }
        },
        "interval_sec": 10.0,
        "json": "/tmp/nfvbench/vsc_1c6n_ndr-imix.json",
        "json_file": "/tmp/nfvbench/vsc_1c6n_ndr-imix.json",
        "l2_loopback": false,
        "log_file": null,
        "loop_vm_name": "nfvbench-loop-vm",
        "measurement": {
            "NDR": 0.001,
            "PDR": 0.1,
            "load_epsilon": 0.1
        },
        "name": "nfvbench_config.cfg",
        "ndr_run": true,
        "no_arp": false,
        "no_cleanup": true,
        "no_traffic": false,
        "no_vswitch_access": false,
        "openrc_file": null,
        "pause_sec": 2.0,
        "pdr_run": false,
        "port": 7555,
        "rate": "ndr",
        "service_chain": "EXT",
        "service_chain_count": 1,
        "service_chain_shared_net": true,
        "single_run": false,
        "sriov": false,
        "std_json": null,
        "std_json_path": null,
        "tg-name": "trex-local",
        "tg-tool": "TRex",
        "traffic": {
            "bidirectional": true,
            "profile": "traffic_profile_IMIX"
        },
        "traffic_generator": {
            "default_profile": "trex-local",
            "gateway_ip_addrs": [
                "172.16.10.10",
                "172.16.20.10"
            ],
            "gateway_ip_addrs_step": "0.0.0.1",
            "generator_profile": [
                {
                    "cores": 7,
                    "interfaces": [
                        {
                            "pci": "3b:00.0",
                            "port": 0,
                            "switch_port": null
                        },
                        {
                            "pci": "3b:00.1",
                            "port": 1,
                            "switch_port": null
                        }
                    ],
                    "intf_speed": "25Gbps",
                    "ip": "127.0.0.1",
                    "name": "trex-local",
                    "software_mode": false,
                    "tool": "TRex"
                }
            ],
            "host_name": "nfvbench_tg",
            "ip_addrs": [
                "172.16.64.0/18",
                "172.16.192.0/18"
            ],
            "ip_addrs_step": "0.0.0.1",
            "mac_addrs_left": [
                "52:54:00:00:00:aa"
            ],
            "mac_addrs_right": [
                "52:54:00:00:00:bb"
            ],
            "tg_gateway_ip_addrs": [
                "172.16.10.100",
                "172.16.20.100"
            ],
            "tg_gateway_ip_addrs_step": "0.0.0.1",
            "udp_dst_port": 34101,
            "udp_src_port": 34100
        },
        "traffic_profile": [
            {
                "l2frame_size": [
                    "64"
                ],
                "name": "traffic_profile_64B"
            },
            {
                "l2frame_size": [
                    "IMIX"
                ],
                "name": "traffic_profile_IMIX"
            },
            {
                "l2frame_size": [
                    "1518"
                ],
                "name": "traffic_profile_1518B"
            },
            {
                "l2frame_size": [
                    "64",
                    "IMIX"
                ],
                "name": "traffic_profile_2sizes"
            },
            {
                "l2frame_size": [
                    "64",
                    "IMIX",
                    "1518"
                ],
                "name": "traffic_profile_3sizes"
            }
        ],
        "unidir_reverse_traffic_pps": 1,
        "use_sriov_middle_net": false,
        "user_label": null,
        "vlan_tagging": false,
        "vlans": [
            1070,
            1064
        ],
        "vm_forwarder": "vpp",
        "vm_image_file": null
    },
    "date": "2018-12-07 18:17:28",
    "nfvbench_version": "2.0.5"
}