{
    "benchmarks": {
        "network": {
            "service_chain": {
                "EXT": {
                    "result": {
                        "bidirectional": true,
                        "compute_nodes": {},
                        "flow_count": 1024,
                        "profile": "traffic_profile_2sizes",
                        "result": {
                            "64": {
                                "iteration_stats": {
                                    "ndr_pdr": [
                                        {
                                            "drop_pct": 723421580,
                                            "drop_percentage": 88.15831008276011,
                                            "rx_pkts": 97172167,
                                            "rx_pps": 3524312.3851466156,
                                            "time_ms": 1543564566425,
                                            "total_tx_pps": 27353124,
                                            "tx_pkts": 820593747,
                                            "tx_pps": 29761904
                                        },
                                        {
                                            "drop_pct": 348747494,
                                            "drop_percentage": 78.11946935382667,
                                            "rx_pkts": 97680902,
                                            "rx_pps": 3256031.262802343,
                                            "time_ms": 1543564598470,
                                            "total_tx_pps": 14880946,
                                            "tx_pkts": 446428396,
                                            "tx_pps": 14880952
                                        },
                                        {
                                            "drop_pct": 127835876,
                                            "drop_percentage": 57.27076692053852,
                                            "rx_pkts": 95377262,
                                            "rx_pps": 3179258.3322613924,
                                            "time_ms": 1543564630517,
                                            "total_tx_pps": 7440437,
                                            "tx_pkts": 223213138,
                                            "tx_pps": 7440476
                                        },
                                        {
                                            "drop_pct": 0,
                                            "drop_percentage": 0.0,
                                            "rx_pkts": 111607248,
                                            "rx_pps": 3720238.0,
                                            "time_ms": 1543564662561,
                                            "total_tx_pps": 3720241,
                                            "tx_pkts": 111607248,
                                            "tx_pps": 3720238
                                        },
                                        {
                                            "drop_pct": 66184878,
                                            "drop_percentage": 39.53460861298503,
                                            "rx_pkts": 101225096,
                                            "rx_pps": 3374184.096188773,
                                            "time_ms": 1543564694608,
                                            "total_tx_pps": 5580332,
                                            "tx_pkts": 167409974,
                                            "tx_pps": 5580356
                                        },
                                        {
                                            "drop_pct": 31594136,
                                            "drop_percentage": 22.64677222881442,
                                            "rx_pkts": 107914204,
                                            "rx_pps": 3597154.056914332,
                                            "time_ms": 1543564726652,
                                            "total_tx_pps": 4650278,
                                            "tx_pkts": 139508340,
                                            "tx_pps": 4650296
                                        },
                                        {
                                            "drop_pct": 15591688,
                                            "drop_percentage": 12.417959940669126,
                                            "rx_pkts": 109965876,
                                            "rx_pps": 3665541.3447095547,
                                            "time_ms": 1543564758696,
                                            "total_tx_pps": 4185252,
                                            "tx_pkts": 125557564,
                                            "tx_pps": 4185266
                                        },
                                        {
                                            "drop_pct": 6733822,
                                            "drop_percentage": 5.678585743472089,
                                            "rx_pkts": 111848908,
                                            "rx_pps": 3728291.5884531923,
                                            "time_ms": 1543564790742,
                                            "total_tx_pps": 3952757,
                                            "tx_pkts": 118582730,
                                            "tx_pps": 3952752
                                        },
                                        {
                                            "drop_pct": 1998000,
                                            "drop_percentage": 1.73596328585355,
                                            "rx_pkts": 113096600,
                                            "rx_pps": 3769893.8726960258,
                                            "time_ms": 1543564822788,
                                            "total_tx_pps": 3836486,
                                            "tx_pkts": 115094600,
                                            "tx_pps": 3836494
                                        },
                                        {
                                            "drop_pct": 278985,
                                            "drop_percentage": 0.24612538555320873,
                                            "rx_pkts": 113071777,
                                            "rx_pps": 3769066.4821148883,
                                            "time_ms": 1543564854833,
                                            "total_tx_pps": 3778358,
                                            "tx_pkts": 113350762,
                                            "tx_pps": 3778366
                                        },
                                        {
                                            "drop_pct": 0,
                                            "drop_percentage": 0.0,
                                            "ndr_pps": 1874651,
                                            "rx_pkts": 112478812,
                                            "rx_pps": 3749302.0,
                                            "time_ms": 1543564886879,
                                            "total_tx_pps": 3749293,
                                            "tx_pkts": 112478812,
                                            "tx_pps": 3749302
                                        }
                                    ]
                                },
                                "ndr": {
                                    "duration_sec": 30.0,
                                    "initial_rate_type": "rate_percent",
                                    "l2frame_size": "64",
                                    "load_percent_per_direction": 12.59765625,
                                    "rate_bps": 2519531250.0,
                                    "rate_percent": 25.1953125,
                                    "rate_pps": 3749302,
                                    "stats": {
                                        "0": {
                                            "avg_delay_usec": 786,
                                            "drop_pct": 0,
                                            "drop_percentage": 0.0,
                                            "max_delay_usec": 1019,
                                            "min_delay_usec": 40,
                                            "rx_pkts": 56239406,
                                            "tx_pkts": 56239406
                                        },
                                        "1": {
                                            "avg_delay_usec": 887,
                                            "drop_pct": 0,
                                            "drop_percentage": 0.0,
                                            "max_delay_usec": 1111,
                                            "min_delay_usec": 30,
                                            "rx_pkts": 56239406,
                                            "tx_pkts": 56239406
                                        },
                                        "overall": {
                                            "avg_delay_usec": 836,
                                            "drop_pct": 0,
                                            "drop_percentage": 0.0,
                                            "max_delay_usec": 1111,
                                            "min_delay_usec": 30,
                                            "rx_pkts": 112478812,
                                            "tx_pkts": 112478812
                                        },
                                        "total_tx_rate": 3749293
                                    },
                                    "time_taken_sec": 352.520711183548,
                                    "timestamp_sec": 1543564886.879856
                                }
                            },
                            "IMIX": {
                                "iteration_stats": {
                                    "ndr_pdr": [
                                        {
                                            "drop_pct": 150825863,
                                            "drop_percentage": 76.78689945657027,
                                            "rx_pkts": 45595485,
                                            "rx_pps": 1519844.79547829,
                                            "time_ms": 1543564918961,
                                            "total_tx_pps": 6547378,
                                            "tx_pkts": 196421348,
                                            "tx_pps": 6547358
                                        },
                                        {
                                            "drop_pct": 50028188,
                                            "drop_percentage": 50.93978499760748,
                                            "rx_pkts": 48182254,
                                            "rx_pps": 1606073.4652860232,
                                            "time_ms": 1543564951009,
                                            "total_tx_pps": 3273681,
                                            "tx_pkts": 98210442,
                                            "tx_pps": 3273678
                                        },
                                        {
                                            "drop_pct": 0,
                                            "drop_percentage": 0.0,
                                            "rx_pkts": 49105336,
                                            "rx_pps": 1636838.0,
                                            "time_ms": 1543564983056,
                                            "total_tx_pps": 1636844,
                                            "tx_pkts": 49105336,
                                            "tx_pps": 1636838
                                        },
                                        {
                                            "drop_pct": 19989181,
                                            "drop_percentage": 27.137831948382843,
                                            "rx_pkts": 53668807,
                                            "rx_pps": 1788954.2100607743,
                                            "time_ms": 1543565015102,
                                            "total_tx_pps": 2455266,
                                            "tx_pkts": 73657988,
                                            "tx_pps": 2455258
                                        },
                                        {
                                            "drop_pct": 831983,
                                            "drop_percentage": 1.3554255927827326,
                                            "rx_pkts": 60549697,
                                            "rx_pps": 2018315.3417673805,
                                            "time_ms": 1543565047146,
                                            "total_tx_pps": 2046056,
                                            "tx_pkts": 61381680,
                                            "tx_pps": 2046048
                                        },
                                        {
                                            "drop_pct": 0,
                                            "drop_percentage": 0.0,
                                            "rx_pkts": 55243464,
                                            "rx_pps": 1841444.0,
                                            "time_ms": 1543565079192,
                                            "total_tx_pps": 1841448,
                                            "tx_pkts": 55243464,
                                            "tx_pps": 1841444
                                        },
                                        {
                                            "drop_pct": 0,
                                            "drop_percentage": 0.0,
                                            "rx_pkts": 58312580,
                                            "rx_pps": 1943746.0,
                                            "time_ms": 1543565111236,
                                            "total_tx_pps": 1943752,
                                            "tx_pkts": 58312580,
                                            "tx_pps": 1943746
                                        },
                                        {
                                            "drop_pct": 0,
                                            "drop_percentage": 0.0,
                                            "rx_pkts": 59847110,
                                            "rx_pps": 1994898.0,
                                            "time_ms": 1543565143281,
                                            "total_tx_pps": 1994903,
                                            "tx_pkts": 59847110,
                                            "tx_pps": 1994898
                                        },
                                        {
                                            "drop_pct": 0,
                                            "drop_percentage": 0.0,
                                            "rx_pkts": 60614378,
                                            "rx_pps": 2020474.0,
                                            "time_ms": 1543565175327,
                                            "total_tx_pps": 2020479,
                                            "tx_pkts": 60614378,
                                            "tx_pps": 2020474
                                        },
                                        {
                                            "drop_pct": 4015186,
                                            "drop_percentage": 6.5824862238142305,
                                            "rx_pkts": 56982830,
                                            "rx_pps": 1899420.9406056746,
                                            "time_ms": 1543565207374,
                                            "total_tx_pps": 2033267,
                                            "tx_pkts": 60998016,
                                            "tx_pps": 2033260
                                        },
                                        {
                                            "drop_pct": 0,
                                            "drop_percentage": 0.0,
                                            "ndr_pps": 1013434,
                                            "rx_pkts": 60806202,
                                            "rx_pps": 2026868.0,
                                            "time_ms": 1543565239418,
                                            "total_tx_pps": 2026873,
                                            "tx_pkts": 60806202,
                                            "tx_pps": 2026868
                                        }
                                    ]
                                },
                                "ndr": {
                                    "duration_sec": 30.0,
                                    "initial_rate_type": "rate_percent",
                                    "l2frame_size": "IMIX",
                                    "load_percent_per_direction": 30.95703125,
                                    "rate_bps": 6191406250.0,
                                    "rate_percent": 61.9140625,
                                    "rate_pps": 2026868,
                                    "stats": {
                                        "0": {
                                            "avg_delay_usec": 279,
                                            "drop_pct": 0,
                                            "drop_percentage": 0.0,
                                            "max_delay_usec": 552,
                                            "min_delay_usec": 20,
                                            "rx_pkts": 30403101,
                                            "tx_pkts": 30403101
                                        },
                                        "1": {
                                            "avg_delay_usec": 306,
                                            "drop_pct": 0,
                                            "drop_percentage": 0.0,
                                            "max_delay_usec": 618,
                                            "min_delay_usec": 20,
                                            "rx_pkts": 30403101,
                                            "tx_pkts": 30403101
                                        },
                                        "overall": {
                                            "avg_delay_usec": 292,
                                            "drop_pct": 0,
                                            "drop_percentage": 0.0,
                                            "max_delay_usec": 618,
                                            "min_delay_usec": 20,
                                            "rx_pkts": 60806202,
                                            "tx_pkts": 60806202
                                        },
                                        "total_tx_rate": 2026873
                                    },
                                    "time_taken_sec": 352.49431586265564,
                                    "timestamp_sec": 1543565239.418563
                                }
                            }
                        },
                        "service_chain_count": 1
                    }
                }
            },
            "versions": {
                "Traffic_Generator": {
                    "build_date": "Nov 13 2017",
                    "build_time": "10:58:17",
                    "built_by": "hhaim",
                    "mode": "STL",
                    "version": "v2.32"
                }
            }
        }
    },
    "config": {
        "actual_frame_sizes": [
            "64",
            "IMIX"
        ],
        "availability_zone": null,
        "check_traffic_time_sec": 200,
        "compute_nodes": null,
        "config": "/tmp/nfvbench/nfvbench_config.cfg",
        "debug": false,
        "duration_sec": 30.0,
        "external_networks": {
            "left": "nfvbench-net0",
            "right": "nfvbench-net1"
        },
        "factory_class": "BasicFactory",
        "factory_module": "nfvbench.factory",
        "flavor": {
            "disk": 0,
            "extra_specs": {
                "hw:cpu_policy": "dedicated",
                "hw:mem_page_size": "large"
            },
            "ram": 4096,
            "vcpus": 2
        },
        "flavor_type": "nfvbench.medium",
        "flow_count": 1024,
        "fluentd": [
            {
                "ip": "127.0.0.1",
                "logging_tag": null,
                "port": 24224,
                "result_tag": null
            }
        ],
        "frame_sizes": [
            "64",
            "IMIX"
        ],
        "generator_profile": "trex-local",
        "generic_poll_sec": 2,
        "generic_retry_count": 100,
        "host": "0.0.0.0",
        "internal_networks": {
            "left": {
                "cidr": "172.16.10.0/24",
                "name": "nfvbench-net0",
                "network_type": "vlan",
                "physical_network": null,
                "segmentation_id": null,
                "subnet": "nfvbench-subnet0"
            },
            "middle": {
                "cidr": "192.168.3.0/24",
                "name": "nfvbench-net2",
                "network_type": "vlan",
                "physical_network": null,
                "segmentation_id": null,
                "subnet": "nfvbench-subnet2"
            },
            "right": {
                "cidr": "172.16.20.0/24",
                "name": "nfvbench-net1",
                "network_type": "vlan",
                "physical_network": null,
                "segmentation_id": null,
                "subnet": "nfvbench-subnet1"
            }
        },
        "interval_sec": 10.0,
        "json": "/tmp/nfvbench/csc_1c4n_ndr-1.json",
        "json_file": "/tmp/nfvbench/csc_1c4n_ndr-1.json",
        "l2_loopback": false,
        "log_file": null,
        "loop_vm_name": "nfvbench-loop-vm",
        "measurement": {
            "NDR": 0.001,
            "PDR": 0.1,
            "load_epsilon": 0.1
        },
        "name": "nfvbench_config.cfg",
        "ndr_run": true,
        "no_arp": false,
        "no_cleanup": true,
        "no_traffic": false,
        "no_vswitch_access": false,
        "openrc_file": null,
        "pause_sec": 2.0,
        "pdr_run": false,
        "port": 7555,
        "rate": "ndr",
        "service_chain": "EXT",
        "service_chain_count": 1,
        "service_chain_shared_net": true,
        "single_run": false,
        "sriov": false,
        "std_json": null,
        "std_json_path": null,
        "tg-name": "trex-local",
        "tg-tool": "TRex",
        "traffic": {
            "bidirectional": true,
            "profile": "traffic_profile_2sizes"
        },
        "traffic_generator": {
            "default_profile": "trex-local",
            "gateway_ip_addrs": [
                "172.16.10.10",
                "172.16.20.10"
            ],
            "gateway_ip_addrs_step": "0.0.0.1",
            "generator_profile": [
                {
                    "cores": 7,
                    "interfaces": [
                        {
                            "pci": "1a:00.1",
                            "port": 0,
                            "switch_port": null
                        },
                        {
                            "pci": "1a:00.2",
                            "port": 1,
                            "switch_port": null
                        }
                    ],
                    "intf_speed": "10Gbps",
                    "ip": "127.0.0.1",
                    "name": "trex-local",
                    "software_mode": false,
                    "tool": "TRex"
                }
            ],
            "host_name": "nfvbench_tg",
            "ip_addrs": [
                "172.16.64.0/18",
                "172.16.192.0/18"
            ],
            "ip_addrs_step": "0.0.0.1",
            "mac_addrs_left": [
                "52:54:00:00:00:aa"
            ],
            "mac_addrs_right": [
                "52:54:00:00:00:bb"
            ],
            "tg_gateway_ip_addrs": [
                "172.16.10.100",
                "172.16.20.100"
            ],
            "tg_gateway_ip_addrs_step": "0.0.0.1",
            "udp_dst_port": 34101,
            "udp_src_port": 34100
        },
        "traffic_profile": [
            {
                "l2frame_size": [
                    "64"
                ],
                "name": "traffic_profile_64B"
            },
            {
                "l2frame_size": [
                    "IMIX"
                ],
                "name": "traffic_profile_IMIX"
            },
            {
                "l2frame_size": [
                    "1518"
                ],
                "name": "traffic_profile_1518B"
            },
            {
                "l2frame_size": [
                    "64",
                    "IMIX"
                ],
                "name": "traffic_profile_2sizes"
            },
            {
                "l2frame_size": [
                    "68",
                    "IMIX",
                    "1518"
                ],
                "name": "traffic_profile_3sizes"
            }
        ],
        "unidir_reverse_traffic_pps": 1,
        "use_sriov_middle_net": false,
        "user_label": null,
        "vlan_tagging": false,
        "vlans": [
            1070,
            1064
        ],
        "vm_forwarder": "vpp",
        "vm_image_file": null
    },
    "date": "2018-11-30 07:55:31",
    "nfvbench_version": "2.0.4"
}