{
    "benchmarks": {
        "network": {
            "service_chain": {
                "EXT": {
                    "result": {
                        "bidirectional": true,
                        "compute_nodes": {},
                        "flow_count": 1024,
                        "profile": "traffic_profile_2sizes",
                        "result": {
                            "64": {
                                "iteration_stats": {
                                    "ndr_pdr": [
                                        {
                                            "drop_pct": 1117863403,
                                            "drop_percentage": 98.14017955161145,
                                            "rx_pkts": 21184241,
                                            "rx_pps": 1383794.941054422,
                                            "time_ms": 1543413560561,
                                            "total_tx_pps": 37968254,
                                            "tx_pkts": 1139047644,
                                            "tx_pps": 74404760,
                                            "warning": "WARNING: There is a significant difference between requested TX rate (74404760) and actual TX rate (37968254). The traffic generator may not have sufficient CPU to achieve the requested TX rate."
                                        },
                                        {
                                            "drop_pct": 1094848165,
                                            "drop_percentage": 98.09834535764718,
                                            "rx_pkts": 21223835,
                                            "rx_pps": 707460.7863357385,
                                            "time_ms": 1543413592613,
                                            "total_tx_pps": 37202400,
                                            "tx_pkts": 1116072000,
                                            "tx_pps": 37202380
                                        },
                                        {
                                            "drop_pct": 536881159,
                                            "drop_percentage": 96.20910408687249,
                                            "rx_pkts": 21154553,
                                            "rx_pps": 705151.7515030839,
                                            "time_ms": 1543413624663,
                                            "total_tx_pps": 18601190,
                                            "tx_pkts": 558035712,
                                            "tx_pps": 18601190
                                        },
                                        {
                                            "drop_pct": 258258382,
                                            "drop_percentage": 92.55979121855323,
                                            "rx_pkts": 20759514,
                                            "rx_pps": 691983.6115147115,
                                            "time_ms": 1543413656715,
                                            "total_tx_pps": 9300596,
                                            "tx_pkts": 279017896,
                                            "tx_pps": 9300594
                                        },
                                        {
                                            "drop_pct": 120884698,
                                            "drop_percentage": 86.65014691245298,
                                            "rx_pkts": 18624238,
                                            "rx_pps": 620807.6841360754,
                                            "time_ms": 1543413688763,
                                            "total_tx_pps": 4650297,
                                            "tx_pkts": 139508936,
                                            "tx_pps": 4650296
                                        },
                                        {
                                            "drop_pct": 54919414,
                                            "drop_percentage": 78.73246320321942,
                                            "rx_pkts": 14835058,
                                            "rx_pps": 494501.7064796076,
                                            "time_ms": 1543413720819,
                                            "total_tx_pps": 2325149,
                                            "tx_pkts": 69754472,
                                            "tx_pps": 2325148
                                        },
                                        {
                                            "drop_pct": 25350451,
                                            "drop_percentage": 72.684813404917,
                                            "rx_pkts": 9526781,
                                            "rx_pps": 317559.2574059203,
                                            "time_ms": 1543413752877,
                                            "total_tx_pps": 1162574,
                                            "tx_pkts": 34877232,
                                            "tx_pps": 1162574
                                        },
                                        {
                                            "drop_pct": 10586201,
                                            "drop_percentage": 60.705483414287734,
                                            "rx_pkts": 6852423,
                                            "rx_pps": 228413.5236804234,
                                            "time_ms": 1543413784921,
                                            "total_tx_pps": 581287,
                                            "tx_pkts": 17438624,
                                            "tx_pps": 581286
                                        },
                                        {
                                            "drop_pct": 3236069,
                                            "drop_percentage": 37.113811273183025,
                                            "rx_pkts": 5483243,
                                            "rx_pps": 182773.6766393954,
                                            "time_ms": 1543413816970,
                                            "total_tx_pps": 290643,
                                            "tx_pkts": 8719312,
                                            "tx_pps": 290642
                                        },
                                        {
                                            "drop_pct": -72005,
                                            "drop_percentage": -1.6516211370805403,
                                            "rx_pkts": 4431661,
                                            "rx_pps": 147720.13583640545,
                                            "time_ms": 1543413849018,
                                            "total_tx_pps": 145321,
                                            "tx_pkts": 4359656,
                                            "tx_pps": 145320
                                        },
                                        {
                                            "drop_pct": 1701722,
                                            "drop_percentage": 26.022251283280895,
                                            "ndr_pps": 72660,
                                            "rx_pkts": 4837766,
                                            "rx_pps": 161258.17620767863,
                                            "time_ms": 1543413881060,
                                            "total_tx_pps": 217982,
                                            "tx_pkts": 6539488,
                                            "tx_pps": 217982
                                        }
                                    ]
                                },
                                "ndr": {
                                    "duration_sec": 30.0,
                                    "initial_rate_type": "rate_percent",
                                    "l2frame_size": "64",
                                    "load_percent_per_direction": 0.1953125,
                                    "rate_bps": 97656250.0,
                                    "rate_percent": 0.390625,
                                    "rate_pps": 145320,
                                    "stats": {
                                        "0": {
                                            "avg_delay_usec": 22683,
                                            "drop_pct": 1503974,
                                            "drop_percentage": 68.99507667577441,
                                            "max_delay_usec": 101662,
                                            "min_delay_usec": 20,
                                            "rx_pkts": 675854,
                                            "tx_pkts": 2179828
                                        },
                                        "1": {
                                            "avg_delay_usec": 24753,
                                            "drop_pct": -1575979,
                                            "drop_percentage": -72.2983189499355,
                                            "max_delay_usec": 59414,
                                            "min_delay_usec": 10,
                                            "rx_pkts": 3755807,
                                            "tx_pkts": 2179828
                                        },
                                        "overall": {
                                            "avg_delay_usec": 24437,
                                            "drop_pct": -72005,
                                            "drop_percentage": -1.6516211370805403,
                                            "max_delay_usec": 101662,
                                            "min_delay_usec": 10,
                                            "rx_pkts": 4431661,
                                            "tx_pkts": 4359656
                                        },
                                        "total_tx_rate": 145321
                                    },
                                    "time_taken_sec": 352.546658039093,
                                    "timestamp_sec": 1543413881.061037
                                }
                            },
                            "IMIX": {
                                "iteration_stats": {
                                    "ndr_pdr": [
                                        {
                                            "drop_pct": 419830947,
                                            "drop_percentage": 96.59489287113766,
                                            "rx_pkts": 14799637,
                                            "rx_pps": 557361.4871785608,
                                            "time_ms": 1543413913231,
                                            "total_tx_pps": 14487686,
                                            "tx_pkts": 434630584,
                                            "tx_pps": 16368398,
                                            "warning": "WARNING: There is a significant difference between requested TX rate (16368398) and actual TX rate (14487686). The traffic generator may not have sufficient CPU to achieve the requested TX rate."
                                        },
                                        {
                                            "drop_pct": 230239003,
                                            "drop_percentage": 93.77358727100476,
                                            "rx_pkts": 15287493,
                                            "rx_pps": 509581.9460381741,
                                            "time_ms": 1543413945288,
                                            "total_tx_pps": 8184216,
                                            "tx_pkts": 245526496,
                                            "tx_pps": 8184198
                                        },
                                        {
                                            "drop_pct": 108192081,
                                            "drop_percentage": 88.1304755269008,
                                            "rx_pkts": 14571447,
                                            "rx_pps": 485712.57357320306,
                                            "time_ms": 1543413977339,
                                            "total_tx_pps": 4092117,
                                            "tx_pkts": 122763528,
                                            "tx_pps": 4092098
                                        },
                                        {
                                            "drop_pct": 48538714,
                                            "drop_percentage": 79.0764106243455,
                                            "rx_pkts": 12843326,
                                            "rx_pps": 428106.6819487914,
                                            "time_ms": 1543414009392,
                                            "total_tx_pps": 2046068,
                                            "tx_pkts": 61382040,
                                            "tx_pps": 2046048
                                        },
                                        {
                                            "drop_pct": 21887970,
                                            "drop_percentage": 71.31657591341906,
                                            "rx_pkts": 8803310,
                                            "rx_pps": 293438.3124275038,
                                            "time_ms": 1543414041442,
                                            "total_tx_pps": 1023042,
                                            "tx_pkts": 30691280,
                                            "tx_pps": 1023024
                                        },
                                        {
                                            "drop_pct": 9115706,
                                            "drop_percentage": 59.40152660851958,
                                            "rx_pkts": 6230206,
                                            "rx_pps": 207666.0632142293,
                                            "time_ms": 1543414073499,
                                            "total_tx_pps": 511530,
                                            "tx_pkts": 15345912,
                                            "tx_pps": 511512
                                        },
                                        {
                                            "drop_pct": 2760371,
                                            "drop_percentage": 35.974070351654014,
                                            "rx_pkts": 4912853,
                                            "rx_pps": 163750.15663142377,
                                            "time_ms": 1543414105550,
                                            "total_tx_pps": 255774,
                                            "tx_pkts": 7673224,
                                            "tx_pps": 255756
                                        },
                                        {
                                            "drop_pct": -281505,
                                            "drop_percentage": -7.336820541690123,
                                            "rx_pkts": 4118385,
                                            "rx_pps": 137260.1793723025,
                                            "time_ms": 1543414137601,
                                            "total_tx_pps": 127896,
                                            "tx_pkts": 3836880,
                                            "tx_pps": 127878
                                        },
                                        {
                                            "drop_pct": 1257064,
                                            "drop_percentage": 21.842776160649002,
                                            "rx_pkts": 4497992,
                                            "rx_pps": 149918.0604796895,
                                            "time_ms": 1543414169652,
                                            "total_tx_pps": 191835,
                                            "tx_pkts": 5755056,
                                            "tx_pps": 191816
                                        },
                                        {
                                            "drop_pct": 254674,
                                            "drop_percentage": 5.3101777329252124,
                                            "rx_pkts": 4541286,
                                            "rx_pps": 151357.89330102838,
                                            "time_ms": 1543414201703,
                                            "total_tx_pps": 159865,
                                            "tx_pkts": 4795960,
                                            "tx_pps": 159846
                                        },
                                        {
                                            "drop_pct": -39139,
                                            "drop_percentage": -0.9067459545216132,
                                            "ndr_pps": 71931,
                                            "rx_pkts": 4355563,
                                            "rx_pps": 145166.46286509387,
                                            "time_ms": 1543414233750,
                                            "total_tx_pps": 143880,
                                            "tx_pkts": 4316424,
                                            "tx_pps": 143862
                                        }
                                    ]
                                },
                                "ndr": {
                                    "duration_sec": 30.0,
                                    "initial_rate_type": "rate_percent",
                                    "l2frame_size": "IMIX",
                                    "load_percent_per_direction": 0.87890625,
                                    "rate_bps": 439453124.0,
                                    "rate_percent": 1.7578125,
                                    "rate_pps": 143862,
                                    "stats": {
                                        "0": {
                                            "avg_delay_usec": 34288,
                                            "drop_pct": 1489427,
                                            "drop_percentage": 69.0120803702324,
                                            "max_delay_usec": 188970,
                                            "min_delay_usec": 10,
                                            "rx_pkts": 668785,
                                            "tx_pkts": 2158212
                                        },
                                        "1": {
                                            "avg_delay_usec": 30238,
                                            "drop_pct": -1528566,
                                            "drop_percentage": -70.82557227927562,
                                            "max_delay_usec": 48157,
                                            "min_delay_usec": 10,
                                            "rx_pkts": 3686778,
                                            "tx_pkts": 2158212
                                        },
                                        "overall": {
                                            "avg_delay_usec": 30859,
                                            "drop_pct": -39139,
                                            "drop_percentage": -0.9067459545216132,
                                            "max_delay_usec": 188970,
                                            "min_delay_usec": 10,
                                            "rx_pkts": 4355563,
                                            "tx_pkts": 4316424
                                        },
                                        "total_tx_rate": 143880
                                    },
                                    "time_taken_sec": 352.5691010951996,
                                    "timestamp_sec": 1543414233.751193
                                }
                            }
                        },
                        "service_chain_count": 4
                    }
                }
            },
            "versions": {
                "Traffic_Generator": {
                    "build_date": "Nov 13 2017",
                    "build_time": "10:58:17",
                    "built_by": "hhaim",
                    "mode": "STL",
                    "version": "v2.32"
                }
            }
        }
    },
    "config": {
        "availability_zone": null,
        "check_traffic_time_sec": 200,
        "compute_nodes": null,
        "config": "/tmp/nfvbench/nfvbench_config.cfg",
        "debug": false,
        "duration_sec": 30.0,
        "external_networks": {
            "left": "nfvbench-net0",
            "right": "nfvbench-net1"
        },
        "factory_class": "BasicFactory",
        "factory_module": "nfvbench.factory",
        "flavor": {
            "disk": 0,
            "extra_specs": {
                "hw:cpu_policy": "dedicated",
                "hw:mem_page_size": "large"
            },
            "ram": 4096,
            "vcpus": 2
        },
        "flavor_type": "nfvbench.medium",
        "flow_count": 1024,
        "fluentd": [
            {
                "ip": "127.0.0.1",
                "logging_tag": null,
                "port": 24224,
                "result_tag": null
            }
        ],
        "frame_sizes": [
            "64",
            "IMIX"
        ],
        "generator_profile": "trex-local",
        "generic_poll_sec": 2,
        "generic_retry_count": 100,
        "host": "0.0.0.0",
        "internal_networks": {
            "left": {
                "cidr": "172.16.10.0/24",
                "name": "nfvbench-net0",
                "network_type": "vlan",
                "physical_network": null,
                "segmentation_id": null,
                "subnet": "nfvbench-subnet0"
            },
            "middle": {
                "cidr": "192.168.3.0/24",
                "name": "nfvbench-net2",
                "network_type": "vlan",
                "physical_network": null,
                "segmentation_id": null,
                "subnet": "nfvbench-subnet2"
            },
            "right": {
                "cidr": "172.16.20.0/24",
                "name": "nfvbench-net1",
                "network_type": "vlan",
                "physical_network": null,
                "segmentation_id": null,
                "subnet": "nfvbench-subnet1"
            }
        },
        "interval_sec": 10.0,
        "json": "/tmp/nfvbench/vsc_4c2n_ndr-1.json",
        "json_file": "/tmp/nfvbench/vsc_4c2n_ndr-1.json",
        "l2_loopback": false,
        "log_file": null,
        "loop_vm_name": "nfvbench-loop-vm",
        "measurement": {
            "NDR": 0.001,
            "PDR": 0.1,
            "load_epsilon": 0.1
        },
        "name": "nfvbench_config.cfg",
        "ndr_run": true,
        "no_arp": false,
        "no_cleanup": true,
        "no_traffic": false,
        "no_vswitch_access": false,
        "openrc_file": null,
        "pause_sec": 2.0,
        "pdr_run": false,
        "port": 7555,
        "rate": "ndr",
        "service_chain": "EXT",
        "service_chain_count": 4,
        "service_chain_shared_net": true,
        "single_run": false,
        "sriov": false,
        "std_json": null,
        "std_json_path": null,
        "tg-name": "trex-local",
        "tg-tool": "TRex",
        "traffic": {
            "bidirectional": true,
            "profile": "traffic_profile_2sizes"
        },
        "traffic_generator": {
            "default_profile": "trex-local",
            "gateway_ip_addrs": [
                "172.16.10.10",
                "172.16.20.10"
            ],
            "gateway_ip_addrs_step": "0.0.0.1",
            "generator_profile": [
                {
                    "cores": 7,
                    "interfaces": [
                        {
                            "pci": "3b:00.0",
                            "port": 0,
                            "switch_port": null
                        },
                        {
                            "pci": "3b:00.1",
                            "port": 1,
                            "switch_port": null
                        }
                    ],
                    "intf_speed": "25Gbps",
                    "ip": "127.0.0.1",
                    "name": "trex-local",
                    "software_mode": false,
                    "tool": "TRex"
                }
            ],
            "host_name": "nfvbench_tg",
            "ip_addrs": [
                "172.16.64.0/18",
                "172.16.192.0/18"
            ],
            "ip_addrs_step": "0.0.0.1",
            "mac_addrs_left": [
                "52:54:00:00:00:aa",
                "52:54:01:00:00:aa",
                "52:54:02:00:00:aa",
                "52:54:03:00:00:aa"
            ],
            "mac_addrs_right": [
                "52:54:00:00:00:bb",
                "52:54:01:00:00:bb",
                "52:54:02:00:00:bb",
                "52:54:03:00:00:bb"
            ],
            "tg_gateway_ip_addrs": [
                "172.16.10.100",
                "172.16.20.100"
            ],
            "tg_gateway_ip_addrs_step": "0.0.0.1",
            "udp_dst_port": 34101,
            "udp_src_port": 34100
        },
        "traffic_profile": [
            {
                "l2frame_size": [
                    "64"
                ],
                "name": "traffic_profile_64B"
            },
            {
                "l2frame_size": [
                    "IMIX"
                ],
                "name": "traffic_profile_IMIX"
            },
            {
                "l2frame_size": [
                    "1518"
                ],
                "name": "traffic_profile_1518B"
            },
            {
                "l2frame_size": [
                    "64",
                    "IMIX"
                ],
                "name": "traffic_profile_2sizes"
            },
            {
                "l2frame_size": [
                    "64",
                    "IMIX",
                    "1518"
                ],
                "name": "traffic_profile_3sizes"
            }
        ],
        "unidir_reverse_traffic_pps": 1,
        "use_sriov_middle_net": false,
        "user_label": null,
        "vlan_tagging": false,
        "vlans": [
            [
                1070,
                1070,
                1070,
                1070
            ],
            [
                1064,
                1064,
                1064,
                1064
            ]
        ],
        "vm_forwarder": "vpp",
        "vm_image_file": null
    },
    "date": "2018-11-28 13:58:15",
    "nfvbench_version": "2.0.5"
}