{
    "benchmarks": {
        "network": {
            "service_chain": {
                "EXT": {
                    "result": {
                        "bidirectional": true,
                        "compute_nodes": {},
                        "flow_count": 1024,
                        "profile": "traffic_profile_2sizes",
                        "result": {
                            "64": {
                                "iteration_stats": {
                                    "ndr_pdr": [
                                        {
                                            "drop_pct": 713648904,
                                            "drop_percentage": 89.71242886609949,
                                            "rx_pkts": 81836084,
                                            "rx_pps": 2922605.3422438176,
                                            "time_ms": 1543407919129,
                                            "total_tx_pps": 26516166,
                                            "tx_pkts": 795484988,
                                            "tx_pps": 28409090
                                        },
                                        {
                                            "drop_pct": 342668570,
                                            "drop_percentage": 80.41279063524225,
                                            "rx_pkts": 83468326,
                                            "rx_pps": 2782273.772589136,
                                            "time_ms": 1543407951182,
                                            "total_tx_pps": 14204563,
                                            "tx_pkts": 426136896,
                                            "tx_pps": 14204544
                                        },
                                        {
                                            "drop_pct": 131156488,
                                            "drop_percentage": 61.55629596969494,
                                            "rx_pkts": 81911056,
                                            "rx_pps": 2730376.4271072275,
                                            "time_ms": 1543407983237,
                                            "total_tx_pps": 7102251,
                                            "tx_pkts": 213067544,
                                            "tx_pps": 7102272
                                        },
                                        {
                                            "drop_pct": 19126452,
                                            "drop_percentage": 17.953336470728175,
                                            "rx_pkts": 87407796,
                                            "rx_pps": 2913588.6053868425,
                                            "time_ms": 1543408015296,
                                            "total_tx_pps": 3551141,
                                            "tx_pkts": 106534248,
                                            "tx_pps": 3551136
                                        },
                                        {
                                            "drop_pct": 0,
                                            "drop_percentage": 0.0,
                                            "rx_pkts": 53267024,
                                            "rx_pps": 1775568.0,
                                            "time_ms": 1543408047344,
                                            "total_tx_pps": 1775567,
                                            "tx_pkts": 53267024,
                                            "tx_pps": 1775568
                                        },
                                        {
                                            "drop_pct": 0,
                                            "drop_percentage": 0.0,
                                            "rx_pkts": 79900472,
                                            "rx_pps": 2663352.0,
                                            "time_ms": 1543408079402,
                                            "total_tx_pps": 2663349,
                                            "tx_pkts": 79900472,
                                            "tx_pps": 2663352
                                        },
                                        {
                                            "drop_pct": 7640480,
                                            "drop_percentage": 8.196423048232447,
                                            "rx_pkts": 85576768,
                                            "rx_pps": 2852561.1366191804,
                                            "time_ms": 1543408111461,
                                            "total_tx_pps": 3107241,
                                            "tx_pkts": 93217248,
                                            "tx_pps": 3107244
                                        },
                                        {
                                            "drop_pct": 85196,
                                            "drop_percentage": 0.09842548794531537,
                                            "rx_pkts": 86473684,
                                            "rx_pps": 2882458.131364824,
                                            "time_ms": 1543408143519,
                                            "total_tx_pps": 2885296,
                                            "tx_pkts": 86558880,
                                            "tx_pps": 2885298
                                        },
                                        {
                                            "drop_pct": 0,
                                            "drop_percentage": 0.0,
                                            "rx_pkts": 83229776,
                                            "rx_pps": 2774324.0,
                                            "time_ms": 1543408175574,
                                            "total_tx_pps": 2774325,
                                            "tx_pkts": 83229776,
                                            "tx_pps": 2774324
                                        },
                                        {
                                            "drop_pct": 0,
                                            "drop_percentage": 0.0,
                                            "rx_pkts": 84894480,
                                            "rx_pps": 2829810.0,
                                            "time_ms": 1543408207631,
                                            "total_tx_pps": 2829816,
                                            "tx_pkts": 84894480,
                                            "tx_pps": 2829810
                                        },
                                        {
                                            "drop_pct": 0,
                                            "drop_percentage": 0.0,
                                            "ndr_pps": 1428777,
                                            "rx_pkts": 85726680,
                                            "rx_pps": 2857554.0,
                                            "time_ms": 1543408239688,
                                            "total_tx_pps": 2857556,
                                            "tx_pkts": 85726680,
                                            "tx_pps": 2857554
                                        }
                                    ]
                                },
                                "ndr": {
                                    "duration_sec": 30.0,
                                    "initial_rate_type": "rate_percent",
                                    "l2frame_size": "64",
                                    "load_percent_per_direction": 10.05859375,
                                    "rate_bps": 2011718750.0,
                                    "rate_percent": 20.1171875,
                                    "rate_pps": 2857554,
                                    "stats": {
                                        "0": {
                                            "avg_delay_usec": 454,
                                            "drop_pct": 0,
                                            "drop_percentage": 0.0,
                                            "max_delay_usec": 686,
                                            "min_delay_usec": 10,
                                            "rx_pkts": 42863340,
                                            "tx_pkts": 42863340
                                        },
                                        "1": {
                                            "avg_delay_usec": 442,
                                            "drop_pct": 0,
                                            "drop_percentage": 0.0,
                                            "max_delay_usec": 652,
                                            "min_delay_usec": 20,
                                            "rx_pkts": 42863340,
                                            "tx_pkts": 42863340
                                        },
                                        "overall": {
                                            "avg_delay_usec": 448,
                                            "drop_pct": 0,
                                            "drop_percentage": 0.0,
                                            "max_delay_usec": 686,
                                            "min_delay_usec": 10,
                                            "rx_pkts": 85726680,
                                            "tx_pkts": 85726680
                                        },
                                        "total_tx_rate": 2857556
                                    },
                                    "time_taken_sec": 352.60998797416687,
                                    "timestamp_sec": 1543408239.688579
                                }
                            },
                            "IMIX": {
                                "iteration_stats": {
                                    "ndr_pdr": [
                                        {
                                            "drop_pct": 154073527,
                                            "drop_percentage": 78.44041072326279,
                                            "rx_pkts": 42347585,
                                            "rx_pps": 1411583.4932775958,
                                            "time_ms": 1543408271858,
                                            "total_tx_pps": 6547370,
                                            "tx_pkts": 196421112,
                                            "tx_pps": 6547358
                                        },
                                        {
                                            "drop_pct": 54286630,
                                            "drop_percentage": 55.27555838194436,
                                            "rx_pkts": 43924282,
                                            "rx_pps": 1464134.2058731318,
                                            "time_ms": 1543408303912,
                                            "total_tx_pps": 3273697,
                                            "tx_pkts": 98210912,
                                            "tx_pps": 3273678
                                        },
                                        {
                                            "drop_pct": 0,
                                            "drop_percentage": 0.0,
                                            "rx_pkts": 49105744,
                                            "rx_pps": 1636838.0,
                                            "time_ms": 1543408335969,
                                            "total_tx_pps": 1636858,
                                            "tx_pkts": 49105744,
                                            "tx_pps": 1636838
                                        },
                                        {
                                            "drop_pct": 28417741,
                                            "drop_percentage": 38.580469345231144,
                                            "rx_pkts": 45240619,
                                            "rx_pps": 1508007.9399636646,
                                            "time_ms": 1543408368023,
                                            "total_tx_pps": 2455278,
                                            "tx_pkts": 73658360,
                                            "tx_pps": 2455258
                                        },
                                        {
                                            "drop_pct": 13729060,
                                            "drop_percentage": 22.36657497860938,
                                            "rx_pkts": 47652980,
                                            "rx_pps": 1588417.1399816624,
                                            "time_ms": 1543408400078,
                                            "total_tx_pps": 2046068,
                                            "tx_pkts": 61382040,
                                            "tx_pps": 2046048
                                        },
                                        {
                                            "drop_pct": 6667844,
                                            "drop_percentage": 12.069831145845491,
                                            "rx_pkts": 48576044,
                                            "rx_pps": 1619184.818554697,
                                            "time_ms": 1543408432133,
                                            "total_tx_pps": 1841462,
                                            "tx_pkts": 55243888,
                                            "tx_pps": 1841444
                                        },
                                        {
                                            "drop_pct": 3093772,
                                            "drop_percentage": 5.929626135394343,
                                            "rx_pkts": 49081052,
                                            "rx_pps": 1636017.38143638,
                                            "time_ms": 1543408464189,
                                            "total_tx_pps": 1739160,
                                            "tx_pkts": 52174824,
                                            "tx_pps": 1739142
                                        },
                                        {
                                            "drop_pct": 0,
                                            "drop_percentage": 0.0,
                                            "rx_pkts": 50640272,
                                            "rx_pps": 1687990.0,
                                            "time_ms": 1543408496245,
                                            "total_tx_pps": 1688009,
                                            "tx_pkts": 50640272,
                                            "tx_pps": 1687990
                                        },
                                        {
                                            "drop_pct": 0,
                                            "drop_percentage": 0.0,
                                            "rx_pkts": 51407544,
                                            "rx_pps": 1713566.0,
                                            "time_ms": 1543408528299,
                                            "total_tx_pps": 1713584,
                                            "tx_pkts": 51407544,
                                            "tx_pps": 1713566
                                        },
                                        {
                                            "drop_pct": 0,
                                            "drop_percentage": 0.0,
                                            "rx_pkts": 51791176,
                                            "rx_pps": 1726354.0,
                                            "time_ms": 1543408560356,
                                            "total_tx_pps": 1726372,
                                            "tx_pkts": 51791176,
                                            "tx_pps": 1726354
                                        },
                                        {
                                            "drop_pct": 0,
                                            "drop_percentage": 0.0,
                                            "ndr_pps": 866374,
                                            "rx_pkts": 51982992,
                                            "rx_pps": 1732748.0,
                                            "time_ms": 1543408592412,
                                            "total_tx_pps": 1732766,
                                            "tx_pkts": 51982992,
                                            "tx_pps": 1732748
                                        }
                                    ]
                                },
                                "ndr": {
                                    "duration_sec": 30.0,
                                    "initial_rate_type": "rate_percent",
                                    "l2frame_size": "IMIX",
                                    "load_percent_per_direction": 26.46484375,
                                    "rate_bps": 5292968750.0,
                                    "rate_percent": 52.9296875,
                                    "rate_pps": 1732748,
                                    "stats": {
                                        "0": {
                                            "avg_delay_usec": 290,
                                            "drop_pct": 0,
                                            "drop_percentage": 0.0,
                                            "max_delay_usec": 454,
                                            "min_delay_usec": 20,
                                            "rx_pkts": 25991496,
                                            "tx_pkts": 25991496
                                        },
                                        "1": {
                                            "avg_delay_usec": 278,
                                            "drop_pct": 0,
                                            "drop_percentage": 0.0,
                                            "max_delay_usec": 424,
                                            "min_delay_usec": 2,
                                            "rx_pkts": 25991496,
                                            "tx_pkts": 25991496
                                        },
                                        "overall": {
                                            "avg_delay_usec": 284,
                                            "drop_pct": 0,
                                            "drop_percentage": 0.0,
                                            "max_delay_usec": 454,
                                            "min_delay_usec": 2,
                                            "rx_pkts": 51982992,
                                            "tx_pkts": 51982992
                                        },
                                        "total_tx_rate": 1732766
                                    },
                                    "time_taken_sec": 352.60249304771423,
                                    "timestamp_sec": 1543408592.412318
                                }
                            }
                        },
                        "service_chain_count": 4
                    }
                }
            },
            "versions": {
                "Traffic_Generator": {
                    "build_date": "Nov 13 2017",
                    "build_time": "10:58:17",
                    "built_by": "hhaim",
                    "mode": "STL",
                    "version": "v2.32"
                }
            }
        }
    },
    "config": {
        "actual_frame_sizes": [
            "64",
            "IMIX"
        ],
        "availability_zone": null,
        "check_traffic_time_sec": 200,
        "compute_nodes": null,
        "config": "/tmp/nfvbench/nfvbench_config.cfg",
        "debug": false,
        "duration_sec": 30.0,
        "external_networks": {
            "left": "nfvbench-net0",
            "right": "nfvbench-net1"
        },
        "factory_class": "BasicFactory",
        "factory_module": "nfvbench.factory",
        "flavor": {
            "disk": 0,
            "extra_specs": {
                "hw:cpu_policy": "dedicated",
                "hw:mem_page_size": "large"
            },
            "ram": 4096,
            "vcpus": 2
        },
        "flavor_type": "nfvbench.medium",
        "flow_count": 1024,
        "fluentd": [
            {
                "ip": "127.0.0.1",
                "logging_tag": null,
                "port": 24224,
                "result_tag": null
            }
        ],
        "frame_sizes": [
            "64",
            "IMIX"
        ],
        "generator_profile": "trex-local",
        "generic_poll_sec": 2,
        "generic_retry_count": 100,
        "host": "0.0.0.0",
        "internal_networks": {
            "left": {
                "cidr": "172.16.10.0/24",
                "name": "nfvbench-net0",
                "network_type": "vlan",
                "physical_network": null,
                "segmentation_id": null,
                "subnet": "nfvbench-subnet0"
            },
            "middle": {
                "cidr": "192.168.3.0/24",
                "name": "nfvbench-net2",
                "network_type": "vlan",
                "physical_network": null,
                "segmentation_id": null,
                "subnet": "nfvbench-subnet2"
            },
            "right": {
                "cidr": "172.16.20.0/24",
                "name": "nfvbench-net1",
                "network_type": "vlan",
                "physical_network": null,
                "segmentation_id": null,
                "subnet": "nfvbench-subnet1"
            }
        },
        "interval_sec": 10.0,
        "json": "/tmp/nfvbench/csc_4c2n_ndr-1.json",
        "json_file": "/tmp/nfvbench/csc_4c2n_ndr-1.json",
        "l2_loopback": false,
        "log_file": null,
        "loop_vm_name": "nfvbench-loop-vm",
        "measurement": {
            "NDR": 0.001,
            "PDR": 0.1,
            "load_epsilon": 0.1
        },
        "name": "nfvbench_config.cfg",
        "ndr_run": true,
        "no_arp": false,
        "no_cleanup": true,
        "no_traffic": false,
        "no_vswitch_access": false,
        "openrc_file": null,
        "pause_sec": 2.0,
        "pdr_run": false,
        "port": 7555,
        "rate": "ndr",
        "service_chain": "EXT",
        "service_chain_count": 4,
        "service_chain_shared_net": true,
        "single_run": false,
        "sriov": false,
        "std_json": null,
        "std_json_path": null,
        "tg-name": "trex-local",
        "tg-tool": "TRex",
        "traffic": {
            "bidirectional": true,
            "profile": "traffic_profile_2sizes"
        },
        "traffic_generator": {
            "default_profile": "trex-local",
            "gateway_ip_addrs": [
                "172.16.10.10",
                "172.16.20.10"
            ],
            "gateway_ip_addrs_step": "0.0.0.1",
            "generator_profile": [
                {
                    "cores": 7,
                    "interfaces": [
                        {
                            "pci": "1a:00.1",
                            "port": 0,
                            "switch_port": null
                        },
                        {
                            "pci": "1a:00.2",
                            "port": 1,
                            "switch_port": null
                        }
                    ],
                    "intf_speed": "10Gbps",
                    "ip": "127.0.0.1",
                    "name": "trex-local",
                    "software_mode": false,
                    "tool": "TRex"
                }
            ],
            "host_name": "nfvbench_tg",
            "ip_addrs": [
                "172.16.64.0/18",
                "172.16.192.0/18"
            ],
            "ip_addrs_step": "0.0.0.1",
            "mac_addrs_left": [
                "52:54:00:00:00:aa",
                "52:54:01:00:00:aa",
                "52:54:02:00:00:aa",
                "52:54:03:00:00:aa"
            ],
            "mac_addrs_right": [
                "52:54:00:00:00:bb",
                "52:54:01:00:00:bb",
                "52:54:02:00:00:bb",
                "52:54:03:00:00:bb"
            ],
            "tg_gateway_ip_addrs": [
                "172.16.10.100",
                "172.16.20.100"
            ],
            "tg_gateway_ip_addrs_step": "0.0.0.1",
            "udp_dst_port": 34101,
            "udp_src_port": 34100
        },
        "traffic_profile": [
            {
                "l2frame_size": [
                    "64"
                ],
                "name": "traffic_profile_64B"
            },
            {
                "l2frame_size": [
                    "IMIX"
                ],
                "name": "traffic_profile_IMIX"
            },
            {
                "l2frame_size": [
                    "1518"
                ],
                "name": "traffic_profile_1518B"
            },
            {
                "l2frame_size": [
                    "64",
                    "IMIX"
                ],
                "name": "traffic_profile_2sizes"
            },
            {
                "l2frame_size": [
                    "68",
                    "IMIX",
                    "1518"
                ],
                "name": "traffic_profile_3sizes"
            }
        ],
        "unidir_reverse_traffic_pps": 1,
        "use_sriov_middle_net": false,
        "user_label": null,
        "vlan_tagging": false,
        "vlans": [
            [
                1070,
                1070,
                1070,
                1070
            ],
            [
                1064,
                1064,
                1064,
                1064
            ]
        ],
        "vm_forwarder": "vpp",
        "vm_image_file": null
    },
    "date": "2018-11-28 12:24:44",
    "nfvbench_version": "2.0.4"
}
