{
    "benchmarks": {
        "network": {
            "service_chain": {
                "EXT": {
                    "result": {
                        "bidirectional": true,
                        "compute_nodes": {},
                        "flow_count": 1024,
                        "profile": "traffic_profile_2sizes",
                        "result": {
                            "64": {
                                "packet_path_stats": {
                                    "Forward": {
                                        "chains": {
                                            "0": {
                                                "lat_avg_usec": 637,
                                                "lat_max_usec": 777,
                                                "lat_min_usec": 200,
                                                "packets": [
                                                    34687499,
                                                    8759019
                                                ]
                                            },
                                            "1": {
                                                "lat_avg_usec": 638,
                                                "lat_max_usec": 783,
                                                "lat_min_usec": 300,
                                                "packets": [
                                                    34687499,
                                                    8759062
                                                ]
                                            },
                                            "2": {
                                                "lat_avg_usec": 640,
                                                "lat_max_usec": 836,
                                                "lat_min_usec": 200,
                                                "packets": [
                                                    34687499,
                                                    8759046
                                                ]
                                            },
                                            "3": {
                                                "lat_avg_usec": 640,
                                                "lat_max_usec": 785,
                                                "lat_min_usec": 200,
                                                "packets": [
                                                    34687499,
                                                    8759124
                                                ]
                                            },
                                            "4": {
                                                "lat_avg_usec": 644,
                                                "lat_max_usec": 782,
                                                "lat_min_usec": 300,
                                                "packets": [
                                                    34687499,
                                                    8759149
                                                ]
                                            },
                                            "5": {
                                                "lat_avg_usec": 642,
                                                "lat_max_usec": 772,
                                                "lat_min_usec": 300,
                                                "packets": [
                                                    34687499,
                                                    8759274
                                                ]
                                            },
                                            "6": {
                                                "lat_avg_usec": 650,
                                                "lat_max_usec": 867,
                                                "lat_min_usec": 300,
                                                "packets": [
                                                    34687499,
                                                    8758748
                                                ]
                                            },
                                            "7": {
                                                "lat_avg_usec": 650,
                                                "lat_max_usec": 773,
                                                "lat_min_usec": 200,
                                                "packets": [
                                                    34687499,
                                                    8758721
                                                ]
                                            },
                                            "total": {
                                                "lat_avg_usec": 643,
                                                "lat_max_usec": 867,
                                                "lat_min_usec": 200,
                                                "packets": [
                                                    277499992,
                                                    70072143
                                                ]
                                            }
                                        },
                                        "interfaces": [
                                            "TRex.TX.p0",
                                            "TRex.RX.p1"
                                        ]
                                    },
                                    "Reverse": {
                                        "chains": {
                                            "0": {
                                                "lat_avg_usec": 636,
                                                "lat_max_usec": 763,
                                                "lat_min_usec": 300,
                                                "packets": [
                                                    34687499,
                                                    64424517036
                                                ]
                                            },
                                            "1": {
                                                "lat_avg_usec": 638,
                                                "lat_max_usec": 762,
                                                "lat_min_usec": 200,
                                                "packets": [
                                                    34687499,
                                                    64424517018
                                                ]
                                            },
                                            "2": {
                                                "lat_avg_usec": 638,
                                                "lat_max_usec": 762,
                                                "lat_min_usec": 300,
                                                "packets": [
                                                    34687499,
                                                    8809808
                                                ]
                                            },
                                            "3": {
                                                "lat_avg_usec": 642,
                                                "lat_max_usec": 766,
                                                "lat_min_usec": 300,
                                                "packets": [
                                                    34687499,
                                                    8810023
                                                ]
                                            },
                                            "4": {
                                                "lat_avg_usec": 642,
                                                "lat_max_usec": 766,
                                                "lat_min_usec": 300,
                                                "packets": [
                                                    34687499,
                                                    8809422
                                                ]
                                            },
                                            "5": {
                                                "lat_avg_usec": 647,
                                                "lat_max_usec": 768,
                                                "lat_min_usec": 300,
                                                "packets": [
                                                    34687499,
                                                    8809933
                                                ]
                                            },
                                            "6": {
                                                "lat_avg_usec": 644,
                                                "lat_max_usec": 775,
                                                "lat_min_usec": 300,
                                                "packets": [
                                                    34687499,
                                                    64424517057
                                                ]
                                            },
                                            "7": {
                                                "lat_avg_usec": 651,
                                                "lat_max_usec": 773,
                                                "lat_min_usec": 300,
                                                "packets": [
                                                    34687499,
                                                    8809513
                                                ]
                                            },
                                            "total": {
                                                "lat_avg_usec": 642,
                                                "lat_max_usec": 775,
                                                "lat_min_usec": 200,
                                                "packets": [
                                                    277499992,
                                                    193317599810
                                                ]
                                            }
                                        },
                                        "interfaces": [
                                            "TRex.TX.p1",
                                            "TRex.RX.p0"
                                        ]
                                    }
                                },
                                "run_config": {
                                    "direction-forward": {
                                        "orig": {
                                            "initial_rate_type": "rate_pps",
                                            "rate_bps": 6216000000,
                                            "rate_percent": 62.160000000000004,
                                            "rate_pps": 9250000
                                        },
                                        "rx": {
                                            "initial_rate_type": "rate_pps",
                                            "rate_bps": 1569616003,
                                            "rate_percent": 15.696160032,
                                            "rate_pps": 2335738
                                        },
                                        "tx": {
                                            "initial_rate_type": "rate_pps",
                                            "rate_bps": 6215999820,
                                            "rate_percent": 62.15999820799999,
                                            "rate_pps": 9249999
                                        }
                                    },
                                    "direction-reverse": {
                                        "orig": {
                                            "initial_rate_type": "rate_pps",
                                            "rate_bps": 6216000000,
                                            "rate_percent": 62.160000000000004,
                                            "rate_pps": 9250000
                                        },
                                        "rx": {
                                            "initial_rate_type": "rate_pps",
                                            "rate_bps": 1578698217,
                                            "rate_percent": 15.786982176,
                                            "rate_pps": 2349253
                                        },
                                        "tx": {
                                            "initial_rate_type": "rate_pps",
                                            "rate_bps": 6215999820,
                                            "rate_percent": 62.15999820799999,
                                            "rate_pps": 9249999
                                        }
                                    },
                                    "direction-total": {
                                        "orig": {
                                            "rate_bps": 12432000000.0,
                                            "rate_percent": 124.32000000000001,
                                            "rate_pps": 18500000.0
                                        },
                                        "rx": {
                                            "rate_bps": 3148314220.0,
                                            "rate_percent": 31.483142208,
                                            "rate_pps": 4684991.0
                                        },
                                        "tx": {
                                            "rate_bps": 12431999640.0,
                                            "rate_percent": 124.31999641599998,
                                            "rate_pps": 18499998.0
                                        }
                                    }
                                },
                                "stats": {
                                    "0": {
                                        "drop_rate_percent": 74.60266629485164,
                                        "rx": {
                                            "avg_delay_usec": 642,
                                            "dropped_pkts": 207022393,
                                            "max_delay_usec": 867,
                                            "min_delay_usec": 200,
                                            "pkt_bit_rate": 1203282304,
                                            "pkt_rate": 2350157,
                                            "total_pkt_bytes": 4510566336,
                                            "total_pkts": 70477599
                                        },
                                        "tx": {
                                            "pkt_bit_rate": 4740857344,
                                            "pkt_rate": 9259488,
                                            "total_pkt_bytes": 17759999488,
                                            "total_pkts": 277499992
                                        }
                                    },
                                    "1": {
                                        "drop_rate_percent": 74.7487765693341,
                                        "rx": {
                                            "avg_delay_usec": 642,
                                            "dropped_pkts": 207427849,
                                            "max_delay_usec": 775,
                                            "min_delay_usec": 200,
                                            "pkt_bit_rate": 1195987840,
                                            "pkt_rate": 2335911,
                                            "total_pkt_bytes": 4484617152,
                                            "total_pkts": 70072143
                                        },
                                        "tx": {
                                            "pkt_bit_rate": 4740842496,
                                            "pkt_rate": 9259460,
                                            "total_pkt_bytes": 17759999488,
                                            "total_pkts": 277499992
                                        }
                                    },
                                    "overall": {
                                        "drop_rate_percent": 74.67572143209287,
                                        "rx": {
                                            "avg_delay_usec": 642,
                                            "dropped_pkts": 414450242,
                                            "max_delay_usec": 867,
                                            "min_delay_usec": 200,
                                            "pkt_bit_rate": 1199635072.0,
                                            "pkt_rate": 2343034.0,
                                            "total_pkt_bytes": 8995183488,
                                            "total_pkts": 140549742
                                        },
                                        "tx": {
                                            "pkt_bit_rate": 4740849920.0,
                                            "pkt_rate": 9259474.0,
                                            "total_pkt_bytes": 35519998976,
                                            "total_pkts": 554999984
                                        }
                                    },
                                    "total_tx_rate": 18499999
                                }
                            },
                            "IMIX": {
                                "packet_path_stats": {
                                    "Forward": {
                                        "chains": {
                                            "0": {
                                                "lat_avg_usec": 1144,
                                                "lat_max_usec": 1338,
                                                "lat_min_usec": 300,
                                                "packets": [
                                                    12282694,
                                                    4280707
                                                ]
                                            },
                                            "1": {
                                                "lat_avg_usec": 1157,
                                                "lat_max_usec": 1344,
                                                "lat_min_usec": 300,
                                                "packets": [
                                                    12282694,
                                                    4280882
                                                ]
                                            },
                                            "2": {
                                                "lat_avg_usec": 1166,
                                                "lat_max_usec": 1355,
                                                "lat_min_usec": 300,
                                                "packets": [
                                                    12282694,
                                                    4279974
                                                ]
                                            },
                                            "3": {
                                                "lat_avg_usec": 1175,
                                                "lat_max_usec": 1356,
                                                "lat_min_usec": 300,
                                                "packets": [
                                                    12282694,
                                                    4281007
                                                ]
                                            },
                                            "4": {
                                                "lat_avg_usec": 1183,
                                                "lat_max_usec": 1366,
                                                "lat_min_usec": 300,
                                                "packets": [
                                                    12282694,
                                                    4280589
                                                ]
                                            },
                                            "5": {
                                                "lat_avg_usec": 1194,
                                                "lat_max_usec": 1381,
                                                "lat_min_usec": 300,
                                                "packets": [
                                                    12282694,
                                                    4279152
                                                ]
                                            },
                                            "6": {
                                                "lat_avg_usec": 1199,
                                                "lat_max_usec": 1390,
                                                "lat_min_usec": 300,
                                                "packets": [
                                                    12282694,
                                                    4280991
                                                ]
                                            },
                                            "7": {
                                                "lat_avg_usec": 1204,
                                                "lat_max_usec": 1401,
                                                "lat_min_usec": 300,
                                                "packets": [
                                                    12282694,
                                                    4280109
                                                ]
                                            },
                                            "total": {
                                                "lat_avg_usec": 1178,
                                                "lat_max_usec": 1401,
                                                "lat_min_usec": 300,
                                                "packets": [
                                                    98261552,
                                                    34243411
                                                ]
                                            }
                                        },
                                        "interfaces": [
                                            "TRex.TX.p0",
                                            "TRex.RX.p1"
                                        ]
                                    },
                                    "Reverse": {
                                        "chains": {
                                            "0": {
                                                "lat_avg_usec": 933,
                                                "lat_max_usec": 1183,
                                                "lat_min_usec": 200,
                                                "packets": [
                                                    12281221,
                                                    64424572371
                                                ]
                                            },
                                            "1": {
                                                "lat_avg_usec": 940,
                                                "lat_max_usec": 1171,
                                                "lat_min_usec": 200,
                                                "packets": [
                                                    12281221,
                                                    64424572359
                                                ]
                                            },
                                            "2": {
                                                "lat_avg_usec": 944,
                                                "lat_max_usec": 1166,
                                                "lat_min_usec": 200,
                                                "packets": [
                                                    12281221,
                                                    64424572442
                                                ]
                                            },
                                            "3": {
                                                "lat_avg_usec": 949,
                                                "lat_max_usec": 1176,
                                                "lat_min_usec": 200,
                                                "packets": [
                                                    12281221,
                                                    6166979
                                                ]
                                            },
                                            "4": {
                                                "lat_avg_usec": 954,
                                                "lat_max_usec": 1183,
                                                "lat_min_usec": 200,
                                                "packets": [
                                                    12281221,
                                                    6165900
                                                ]
                                            },
                                            "5": {
                                                "lat_avg_usec": 959,
                                                "lat_max_usec": 1203,
                                                "lat_min_usec": 200,
                                                "packets": [
                                                    12281221,
                                                    6163979
                                                ]
                                            },
                                            "6": {
                                                "lat_avg_usec": 960,
                                                "lat_max_usec": 1208,
                                                "lat_min_usec": 200,
                                                "packets": [
                                                    12281221,
                                                    6166950
                                                ]
                                            },
                                            "7": {
                                                "lat_avg_usec": 967,
                                                "lat_max_usec": 1208,
                                                "lat_min_usec": 200,
                                                "packets": [
                                                    12281221,
                                                    6166576
                                                ]
                                            },
                                            "total": {
                                                "lat_avg_usec": 951,
                                                "lat_max_usec": 1208,
                                                "lat_min_usec": 200,
                                                "packets": [
                                                    98249768,
                                                    193304547556
                                                ]
                                            }
                                        },
                                        "interfaces": [
                                            "TRex.TX.p1",
                                            "TRex.RX.p0"
                                        ]
                                    }
                                },
                                "run_config": {
                                    "direction-forward": {
                                        "orig": {
                                            "initial_rate_type": "rate_pps",
                                            "rate_bps": 28255666666,
                                            "rate_percent": 282.5566666666667,
                                            "rate_pps": 9250000
                                        },
                                        "rx": {
                                            "initial_rate_type": "rate_pps",
                                            "rate_bps": 3486740204,
                                            "rate_percent": 34.86740204488889,
                                            "rate_pps": 1141447
                                        },
                                        "tx": {
                                            "initial_rate_type": "rate_pps",
                                            "rate_bps": 10005209583,
                                            "rate_percent": 100.05209583644445,
                                            "rate_pps": 3275385
                                        }
                                    },
                                    "direction-reverse": {
                                        "orig": {
                                            "initial_rate_type": "rate_pps",
                                            "rate_bps": 28255666666,
                                            "rate_percent": 282.5566666666667,
                                            "rate_pps": 9250000
                                        },
                                        "rx": {
                                            "initial_rate_type": "rate_pps",
                                            "rate_bps": 5023201289,
                                            "rate_percent": 50.23201289111111,
                                            "rate_pps": 1644435
                                        },
                                        "tx": {
                                            "initial_rate_type": "rate_pps",
                                            "rate_bps": 10004009710,
                                            "rate_percent": 100.04009710577778,
                                            "rate_pps": 3274992
                                        }
                                    },
                                    "direction-total": {
                                        "orig": {
                                            "rate_bps": 56511333332.0,
                                            "rate_percent": 565.1133333333333,
                                            "rate_pps": 18500000.0
                                        },
                                        "rx": {
                                            "rate_bps": 8509941493.0,
                                            "rate_percent": 85.099414936,
                                            "rate_pps": 2785882.0
                                        },
                                        "tx": {
                                            "rate_bps": 20009219293.0,
                                            "rate_percent": 200.09219294222223,
                                            "rate_pps": 6550377.0
                                        }
                                    },
                                    "warning": "WARNING: There is a significant difference between requested TX rate (18500000.0) and actual TX rate (6550377). The traffic generator may not have sufficient CPU to achieve the requested TX rate."
                                },
                                "stats": {
                                    "0": {
                                        "drop_rate_percent": 49.78214978733493,
                                        "rx": {
                                            "avg_delay_usec": 1177,
                                            "dropped_pkts": 48916713,
                                            "max_delay_usec": 1401,
                                            "min_delay_usec": 300,
                                            "pkt_bit_rate": 4748293120,
                                            "pkt_rate": 1641926,
                                            "total_pkt_bytes": 17831714603,
                                            "total_pkts": 49333055
                                        },
                                        "tx": {
                                            "pkt_bit_rate": 9469268992,
                                            "pkt_rate": 3271279,
                                            "total_pkt_bytes": 35554240400,
                                            "total_pkts": 98261552
                                        }
                                    },
                                    "1": {
                                        "drop_rate_percent": 65.1585670919854,
                                        "rx": {
                                            "avg_delay_usec": 950,
                                            "dropped_pkts": 64018141,
                                            "max_delay_usec": 1208,
                                            "min_delay_usec": 200,
                                            "pkt_bit_rate": 3467564288,
                                            "pkt_rate": 1140159,
                                            "total_pkt_bytes": 13011499995,
                                            "total_pkts": 34243411
                                        },
                                        "tx": {
                                            "pkt_bit_rate": 9469266944,
                                            "pkt_rate": 3271297,
                                            "total_pkt_bytes": 35549994536,
                                            "total_pkts": 98249768
                                        }
                                    },
                                    "overall": {
                                        "drop_rate_percent": 57.46989740845464,
                                        "rx": {
                                            "avg_delay_usec": 1083,
                                            "dropped_pkts": 112934854,
                                            "max_delay_usec": 1401,
                                            "min_delay_usec": 200,
                                            "pkt_bit_rate": 4107928704.0,
                                            "pkt_rate": 1391042.5,
                                            "total_pkt_bytes": 30843214598,
                                            "total_pkts": 83576466
                                        },
                                        "tx": {
                                            "pkt_bit_rate": 9469267968.0,
                                            "pkt_rate": 3271288.0,
                                            "total_pkt_bytes": 71104234936,
                                            "total_pkts": 196511320
                                        }
                                    },
                                    "total_tx_rate": 6550377
                                }
                            }
                        },
                        "service_chain_count": 8
                    }
                }
            },
            "versions": {
                "Traffic_Generator": {
                    "build_date": "Nov 13 2017",
                    "build_time": "10:58:17",
                    "built_by": "hhaim",
                    "mode": "STL",
                    "version": "v2.32"
                }
            }
        }
    },
    "config": {
        "actual_frame_sizes": [
            "64",
            "IMIX"
        ],
        "availability_zone": null,
        "check_traffic_time_sec": 200,
        "compute_nodes": null,
        "config": "/tmp/nfvbench/nfvbench_config.cfg",
        "debug": false,
        "duration_sec": 30.0,
        "external_networks": {
            "left": "nfvbench-net0",
            "right": "nfvbench-net1"
        },
        "factory_class": "BasicFactory",
        "factory_module": "nfvbench.factory",
        "flavor": {
            "disk": 0,
            "extra_specs": {
                "hw:cpu_policy": "dedicated",
                "hw:mem_page_size": "large"
            },
            "ram": 4096,
            "vcpus": 2
        },
        "flavor_type": "nfvbench.medium",
        "flow_count": 1024,
        "fluentd": [
            {
                "ip": "127.0.0.1",
                "logging_tag": null,
                "port": 24224,
                "result_tag": null
            }
        ],
        "frame_sizes": [
            "64",
            "IMIX"
        ],
        "generator_profile": "trex-local",
        "generic_poll_sec": 2,
        "generic_retry_count": 100,
        "host": "0.0.0.0",
        "internal_networks": {
            "left": {
                "cidr": "172.16.10.0/24",
                "name": "nfvbench-net0",
                "network_type": "vlan",
                "physical_network": null,
                "segmentation_id": null,
                "subnet": "nfvbench-subnet0"
            },
            "middle": {
                "cidr": "192.168.3.0/24",
                "name": "nfvbench-net2",
                "network_type": "vlan",
                "physical_network": null,
                "segmentation_id": null,
                "subnet": "nfvbench-subnet2"
            },
            "right": {
                "cidr": "172.16.20.0/24",
                "name": "nfvbench-net1",
                "network_type": "vlan",
                "physical_network": null,
                "segmentation_id": null,
                "subnet": "nfvbench-subnet1"
            }
        },
        "interval_sec": 10.0,
        "json": "/tmp/nfvbench/csp_8c1n_18500000pps-1.json",
        "json_file": "/tmp/nfvbench/csp_8c1n_18500000pps-1.json",
        "l2_loopback": false,
        "log_file": null,
        "loop_vm_name": "nfvbench-loop-vm",
        "measurement": {
            "NDR": 0.001,
            "PDR": 0.1,
            "load_epsilon": 0.1
        },
        "name": "nfvbench_config.cfg",
        "ndr_run": false,
        "no_arp": false,
        "no_cleanup": true,
        "no_traffic": false,
        "no_vswitch_access": false,
        "openrc_file": null,
        "pause_sec": 2.0,
        "pdr_run": false,
        "port": 7555,
        "rate": "18500000pps",
        "service_chain": "EXT",
        "service_chain_count": 8,
        "service_chain_shared_net": true,
        "single_run": true,
        "sriov": false,
        "std_json": null,
        "std_json_path": null,
        "tg-name": "trex-local",
        "tg-tool": "TRex",
        "traffic": {
            "bidirectional": true,
            "profile": "traffic_profile_2sizes"
        },
        "traffic_generator": {
            "default_profile": "trex-local",
            "gateway_ip_addrs": [
                "172.16.10.10",
                "172.16.20.10"
            ],
            "gateway_ip_addrs_step": "0.0.0.1",
            "generator_profile": [
                {
                    "cores": 7,
                    "interfaces": [
                        {
                            "pci": "1a:00.1",
                            "port": 0,
                            "switch_port": null
                        },
                        {
                            "pci": "1a:00.2",
                            "port": 1,
                            "switch_port": null
                        }
                    ],
                    "intf_speed": "10Gbps",
                    "ip": "127.0.0.1",
                    "name": "trex-local",
                    "software_mode": false,
                    "tool": "TRex"
                }
            ],
            "host_name": "nfvbench_tg",
            "ip_addrs": [
                "172.16.64.0/18",
                "172.16.192.0/18"
            ],
            "ip_addrs_step": "0.0.0.1",
            "mac_addrs_left": [
                "52:54:00:00:00:aa",
                "52:54:01:00:00:aa",
                "52:54:02:00:00:aa",
                "52:54:03:00:00:aa",
                "52:54:04:00:00:aa",
                "52:54:05:00:00:aa",
                "52:54:06:00:00:aa",
                "52:54:07:00:00:aa"
            ],
            "mac_addrs_right": [
                "52:54:00:00:00:bb",
                "52:54:01:00:00:bb",
                "52:54:02:00:00:bb",
                "52:54:03:00:00:bb",
                "52:54:04:00:00:bb",
                "52:54:05:00:00:bb",
                "52:54:06:00:00:bb",
                "52:54:07:00:00:bb"
            ],
            "tg_gateway_ip_addrs": [
                "172.16.10.100",
                "172.16.20.100"
            ],
            "tg_gateway_ip_addrs_step": "0.0.0.1",
            "udp_dst_port": 34101,
            "udp_src_port": 34100
        },
        "traffic_profile": [
            {
                "l2frame_size": [
                    "64"
                ],
                "name": "traffic_profile_64B"
            },
            {
                "l2frame_size": [
                    "IMIX"
                ],
                "name": "traffic_profile_IMIX"
            },
            {
                "l2frame_size": [
                    "1518"
                ],
                "name": "traffic_profile_1518B"
            },
            {
                "l2frame_size": [
                    "64",
                    "IMIX"
                ],
                "name": "traffic_profile_2sizes"
            },
            {
                "l2frame_size": [
                    "68",
                    "IMIX",
                    "1518"
                ],
                "name": "traffic_profile_3sizes"
            }
        ],
        "unidir_reverse_traffic_pps": 1,
        "use_sriov_middle_net": false,
        "user_label": null,
        "vlan_tagging": false,
        "vlans": [
            [
                1070,
                1070,
                1070,
                1070,
                1070,
                1070,
                1070,
                1070
            ],
            [
                1064,
                1064,
                1064,
                1064,
                1064,
                1064,
                1064,
                1064
            ]
        ],
        "vm_forwarder": "vpp",
        "vm_image_file": null
    },
    "date": "2018-11-28 15:33:03",
    "nfvbench_version": "2.0.4"
}